lifeomic_chatbot_tools/__init__.py
lifeomic_chatbot_tools/_utils.py
lifeomic_chatbot_tools/aws/__init__.py
lifeomic_chatbot_tools/aws/alpha.py
lifeomic_chatbot_tools/aws/s3.py
lifeomic_chatbot_tools/ml/__init__.py
lifeomic_chatbot_tools/ml/conv_graph.py
lifeomic_chatbot_tools/ml/dataset.py
lifeomic_chatbot_tools/ml/utils.py
lifeomic_chatbot_tools/persistence/__init__.py
lifeomic_chatbot_tools/persistence/artifact_manager.py
lifeomic_chatbot_tools/persistence/record_store/__init__.py
lifeomic_chatbot_tools/persistence/record_store/base.py
lifeomic_chatbot_tools/persistence/record_store/dynamodb.py
lifeomic_chatbot_tools/persistence/record_store/large.py
lifeomic_chatbot_tools/persistence/record_store/memory.py
lifeomic_chatbot_tools/persistence/serialization.py
lifeomic_chatbot_tools/types/__init__.py
lifeomic_chatbot_tools/types/agent.py
lifeomic_chatbot_tools/types/conversations/__init__.py
lifeomic_chatbot_tools/types/conversations/actions.py
lifeomic_chatbot_tools/types/conversations/conversation.py
lifeomic_chatbot_tools/types/conversations/dialogue_turns.py
lifeomic_chatbot_tools/types/ml.py
lifeomic_chatbot_tools/types/nlu.py
lifeomic_chatbot_tools/types/utils.py
lifeomic_chatbot_tools/utils.py
lifeomic_chatbot_tools/web/__init__.py
lifeomic_chatbot_tools/web/middleware.py
lifeomic_chatbot_tools-9.0.1.dist-info/LICENSE
lifeomic_chatbot_tools-9.0.1.dist-info/METADATA
lifeomic_chatbot_tools-9.0.1.dist-info/WHEEL
lifeomic_chatbot_tools-9.0.1.dist-info/RECORD
