Metadata-Version: 2.3
Name: lifeomic-chatbot-tools
Version: 9.0.1
Summary: Utilities for machine learning, web services, and cloud infrastructure.
License: MIT
Author: LifeOmic Development
Author-email: development@lifeomic.com
Requires-Python: >=3.12.0,<4.0.0
Classifier: License :: OSI Approved :: MIT License
Classifier: Programming Language :: Python :: 3
Classifier: Programming Language :: Python :: 3.12
Classifier: Programming Language :: Python :: 3.13
Provides-Extra: aws
Provides-Extra: ml
Requires-Dist: boto3 (>=1.21.7,<2.0.0) ; extra == "aws"
Requires-Dist: fastapi (>=0.109.1)
Requires-Dist: httpx (>=0.27.2,<0.28.0)
Requires-Dist: loguru (>=0.5.1,<0.6.0)
Requires-Dist: networkx (>=2.5.1,<3.0.0) ; extra == "ml"
Requires-Dist: numpy (>=1.19.2,<2.0.0) ; extra == "ml"
Requires-Dist: pydantic (>=1.10.17,<3)
Requires-Dist: requests (>=2.21.0,<3.0.0)
Requires-Dist: scikit-learn (>=1.1.3,<2.0.0) ; extra == "ml"
Requires-Dist: tenacity (>=9.1.2,<10.0.0) ; extra == "aws"
